loghub/__init__.py
loghub/cli/__init__.py
loghub/cli/common.py
loghub/cli/label_creator.py
loghub/cli/main.py
loghub/core/__init__.py
loghub/core/config.py
loghub/core/formatter.py
loghub/core/labels.py
loghub/core/repo.py
loghub/core/zenhub.py
loghub/external/__init__.py
loghub/external/github.py
loghub/templates/__init__.py
loghub/templates/changelog.txt
loghub/templates/changelog_issue_groups.txt
loghub/templates/changelog_label_groups.txt
loghub/templates/changelog_pr_groups.txt
loghub/templates/release.txt
loghub/templates/release_issue_groups.txt
loghub/templates/release_label_groups.txt
loghub/templates/release_pr_groups.txt
loghub/tests/__init__.py
loghub/tests/test_changelog.py
loghub/tests/test_config.py
loghub/tests/test_formatter.py
loghub/tests/test_github_repo.py
loghub/tests/test_labels.py
loghub/tests/utils.py
loghub-0.5.1.dist-info/AUTHORS.md
loghub-0.5.1.dist-info/LICENSE.txt
loghub-0.5.1.dist-info/METADATA
loghub-0.5.1.dist-info/WHEEL
loghub-0.5.1.dist-info/entry_points.txt
loghub-0.5.1.dist-info/top_level.txt
loghub-0.5.1.dist-info/RECORD
