Metadata-Version: 2.1
Name: loghub
Version: 0.5.1
Summary: Generate changelogs based on Github milestones or tags
Home-page: https://github.com/spyder-ide/loghub
Author: Carlos Cordoba
Author-email: ccordoba12@gmail.com
Maintainer: Carlos Cordoba
Maintainer-email: ccordoba12@gmail.com
License: MIT
Keywords: github zenhub changelog milestone releases
Platform: UNKNOWN
Classifier: Development Status :: 5 - Production/Stable
Classifier: Intended Audience :: Developers
Classifier: License :: OSI Approved :: MIT License
Classifier: Operating System :: OS Independent
Classifier: Programming Language :: Python :: 2
Classifier: Programming Language :: Python :: 2.7
Classifier: Programming Language :: Python :: 3
Classifier: Programming Language :: Python :: 3.5
Classifier: Programming Language :: Python :: 3.6
Classifier: Programming Language :: Python :: 3.7
Classifier: Programming Language :: Python :: 3.8
Requires-Dist: jinja2
Requires-Dist: requests
